circuitpython_functools.py
circuitpython_functools-2.0.2.post0.dist-info/licenses/LICENSE-MIT
circuitpython_functools-2.0.2.post0.dist-info/licenses/LICENSE-PSF
circuitpython_functools-2.0.2.post0.dist-info/METADATA
circuitpython_functools-2.0.2.post0.dist-info/WHEEL
circuitpython_functools-2.0.2.post0.dist-info/top_level.txt
circuitpython_functools-2.0.2.post0.dist-info/RECORD
