Metadata-Version: 2.4
Name: circuitpython-functools
Version: 2.0.2.post0
Summary: A CircuitPython implementation of CPython's functools library
Author-email: Alec Delaney <tekktrik@gmail.com>
License-Expression: MIT AND PSF-2.0
Project-URL: Homepage, https://github.com/tekktrik/CircuitPython_functools
Keywords: adafruit,blinka,circuitpython,micropython,functools,cache,functions,decorators
Classifier: Intended Audience :: Developers
Classifier: Topic :: Software Development :: Libraries
Classifier: Topic :: Software Development :: Embedded Systems
Classifier: Topic :: System :: Hardware
Classifier: Programming Language :: Python :: 3
License-File: LICENSE-MIT
License-File: LICENSE-PSF
Requires-Dist: Adafruit-Blinka
Provides-Extra: optional
Requires-Dist: pre-commit~=4.1; extra == "optional"
Dynamic: license-file
